custom_helpers/__init__.py
custom_helpers/config.py
custom_helpers/import_utils.py
custom_helpers-0.1.0.dist-info/METADATA
custom_helpers-0.1.0.dist-info/WHEEL
custom_helpers-0.1.0.dist-info/top_level.txt
custom_helpers-0.1.0.dist-info/RECORD
