Metadata-Version: 2.1
Name: custom_helpers
Version: 0.1.0
Summary: A set of helper functions
Author: Rodion Khvorostov
Author-email: rodion.khvorostov@jetbrains.com
Requires-Dist: omegaconf
